invectio/__init__.py
invectio/cli.py
invectio/lib.py
invectio/py.typed
invectio-0.2.2.dist-info/LICENSE
invectio-0.2.2.dist-info/METADATA
invectio-0.2.2.dist-info/WHEEL
invectio-0.2.2.dist-info/entry_points.txt
invectio-0.2.2.dist-info/top_level.txt
invectio-0.2.2.dist-info/RECORD
