Metadata-Version: 2.1
Name: invectio
Version: 0.2.2
Summary: Statically analyze sources and extract information about called and exported library functions in Python applications
Home-page: https://github.com/thoth-station/invectio
Author: Fridolin Pokorny
Author-email: fridex.devel@gmail.com
Maintainer: Fridolin Pokorny
Maintainer-email: fridex.devel@gmail.com
License: GPLv3+
Keywords: ast source code analysis thoth library
Classifier: Operating System :: POSIX :: Linux
Classifier: Topic :: Software Development
Classifier: Development Status :: 4 - Beta
Classifier: License :: OSI Approved :: GNU General Public License v3 or later (GPLv3+)
Classifier: Intended Audience :: Developers
Classifier: Programming Language :: Python :: 3
Classifier: Programming Language :: Python :: 3.6
Classifier: Programming Language :: Python :: 3.7
Classifier: Programming Language :: Python :: 3.8
Classifier: Programming Language :: Python :: 3.9
License-File: LICENSE
Requires-Dist: click
Requires-Dist: daiquiri
Requires-Dist: attrs
